LICENSE
README.md
nautobot_ssot_infoblox/__init__.py
nautobot_ssot_infoblox/constant.py
nautobot_ssot_infoblox/diffsync/__init__.py
nautobot_ssot_infoblox/diffsync/adapters/__init__.py
nautobot_ssot_infoblox/diffsync/adapters/infoblox.py
nautobot_ssot_infoblox/diffsync/adapters/nautobot.py
nautobot_ssot_infoblox/diffsync/models/__init__.py
nautobot_ssot_infoblox/diffsync/models/base.py
nautobot_ssot_infoblox/diffsync/models/infoblox.py
nautobot_ssot_infoblox/diffsync/models/nautobot.py
nautobot_ssot_infoblox/jobs.py
nautobot_ssot_infoblox/signals.py
nautobot_ssot_infoblox/static/nautobot_ssot_infoblox/infoblox_logo.png
nautobot_ssot_infoblox/tests/__init__.py
nautobot_ssot_infoblox/tests/fixtures/create_a_record.json
nautobot_ssot_infoblox/tests/fixtures/create_host_record.json
nautobot_ssot_infoblox/tests/fixtures/create_ptr_record.json
nautobot_ssot_infoblox/tests/fixtures/find_network_reference.json
nautobot_ssot_infoblox/tests/fixtures/find_next_available_ip.json
nautobot_ssot_infoblox/tests/fixtures/get_a_record_by_ip.json
nautobot_ssot_infoblox/tests/fixtures/get_a_record_by_name.json
nautobot_ssot_infoblox/tests/fixtures/get_all_dns_views.json
nautobot_ssot_infoblox/tests/fixtures/get_all_ipv4address_networks.json
nautobot_ssot_infoblox/tests/fixtures/get_all_ipv4address_networks_bulk.json
nautobot_ssot_infoblox/tests/fixtures/get_all_ipv4address_networks_large.json
nautobot_ssot_infoblox/tests/fixtures/get_all_ipv4address_networks_medium.json
nautobot_ssot_infoblox/tests/fixtures/get_all_subnets.json
nautobot_ssot_infoblox/tests/fixtures/get_authoritative_zone.json
nautobot_ssot_infoblox/tests/fixtures/get_dhcp_lease_from_hostname.json
nautobot_ssot_infoblox/tests/fixtures/get_dhcp_lease_from_ipv4.json
nautobot_ssot_infoblox/tests/fixtures/get_host_by_ip.json
nautobot_ssot_infoblox/tests/fixtures/get_host_record_by_name.json
nautobot_ssot_infoblox/tests/fixtures/get_ptr_record_by_name.json
nautobot_ssot_infoblox/tests/fixtures/search_ipv4_address.json
nautobot_ssot_infoblox-0.9.0.dist-info/LICENSE
nautobot_ssot_infoblox-0.9.0.dist-info/METADATA
nautobot_ssot_infoblox-0.9.0.dist-info/WHEEL
nautobot_ssot_infoblox-0.9.0.dist-info/RECORD
