Metadata-Version: 2.1
Name: nautobot-ssot-infoblox
Version: 0.9.0
Summary: Nautobot SSoT Infoblox
Home-page: https://github.com/networktocode-llc/nautobot-plugin-ssot-infoblox
License: Apache-2.0
Keywords: nautobot,nautobot-plugin
Author: Network to Code, LLC
Author-email: info@networktocode.com
Requires-Python: >=3.7,<4.0
Classifier: License :: OSI Approved :: Apache Software License
Classifier: Programming Language :: Python :: 3
Classifier: Programming Language :: Python :: 3.7
Classifier: Programming Language :: Python :: 3.8
Classifier: Programming Language :: Python :: 3.9
Classifier: Programming Language :: Python :: 3.10
Classifier: Programming Language :: Python :: 3.11
Requires-Dist: dnspython (>=2.1.0,<3.0.0)
Requires-Dist: nautobot (>=1.4.0,<2.0.0)
Requires-Dist: nautobot-ssot (>=1.1.0,<1.4.0)
Project-URL: Repository, https://github.com/networktocode-llc/nautobot-plugin-ssot-infoblox
